TCalc/__init__.py
TCalc/age_eye.py
TCalc/basic_example.py
TCalc/functions.py
TCalc/tcalc.py
TCalc/test_tcalc.py
TCalc-1.1.1.dist-info/METADATA
TCalc-1.1.1.dist-info/WHEEL
TCalc-1.1.1.dist-info/top_level.txt
TCalc-1.1.1.dist-info/RECORD
