Metadata-Version: 2.1
Name: TCalc
Version: 1.1.1
Summary: Telescope Calculator! A tool for your telescope
Home-page: https://github.com/Bhavesh012/TCalc
Author: Bhavesh Rajpoot, Ryan Keenan, Binod Bhattarai, Dylon Benton
Author-email: 
License: MIT
Keywords: Telescopes Astronomy Eyepiece Magnification
Platform: UNKNOWN
Classifier: Intended Audience :: Science/Research
Classifier: Topic :: Scientific/Engineering :: Astronomy
Classifier: License :: OSI Approved :: MIT License
Classifier: Programming Language :: Python :: 3.6
Requires-Dist: numpy (>=1.21.0)
Requires-Dist: matplotlib (>=3.4.2)
